evalnlp/__init__.py
evalnlp/uter.py
evalnlp/utils.py
evalnlp/uwer.py
evalnlp-0.1.2.dist-info/LICENCE
evalnlp-0.1.2.dist-info/METADATA
evalnlp-0.1.2.dist-info/WHEEL
evalnlp-0.1.2.dist-info/top_level.txt
evalnlp-0.1.2.dist-info/RECORD
