Metadata-Version: 2.1
Name: evalnlp
Version: 0.1.2
Summary: Enhanced evaluation metrics for NLP tasks
Classifier: Programming Language :: Python :: 3
Classifier: License :: OSI Approved :: GNU General Public License v3 (GPLv3)
Classifier: Operating System :: OS Independent
Classifier: Topic :: Scientific/Engineering :: Artificial Intelligence
Requires-Python: >=3.5
License-File: LICENCE
Requires-Dist: textdistance
Requires-Dist: jiwer
